{
  "collapse-filter": false,
  "search": "path:\"Interazione uomo-macchina\"  ",
  "showTags": false,
  "showAttachments": true,
  "hideUnresolved": false,
  "showOrphans": true,
  "collapse-color-groups": true,
  "colorGroups": [
    {
      "query": "path:Statistica  ",
      "color": {
        "a": 1,
        "rgb": 9568010
      }
    },
    {
      "query": "path:AESO  ",
      "color": {
        "a": 1,
        "rgb": 14845746
      }
    }
  ],
  "collapse-display": true,
  "showArrow": false,
  "textFadeMultiplier": -1.1,
  "nodeSizeMultiplier": 1.14417879417879,
  "lineSizeMultiplier": 1.77577962577963,
  "collapse-forces": true,
  "centerStrength": 0,
  "repelStrength": 3.43035343035343,
  "linkStrength": 1,
  "linkDistance": 363,
  "scale": 0.7141449955094118,
  "close": true
}